{
  "API_URL": "<Put your backend's base URL here>",
  "PROLIFIC": "<enable/disable prolific>",
  "DEMO_SESSION": "<enable/disable demo session>",
  "PROLIFIC_REJECT_LINK": "<Prolific rejection link>",
  "PROLIFIC_ACCEPT_LINK": "<Prolific accept link>",
  "GROUP_DECISION_MAKING": "<enable/disable group decision making>",
  "GREETING_TEXT": "<Greeting text>",
  "CURRENT_SESSION_NUMBER_TEXT": "<Current session text>",
  "CURRENT_SESSION_NUMBER": "<Current session number>",
  "TIMER_ENABLED": "<enable/disable timer>",
  "ANIMATED_PROGRESS_BAR": "<enable/disable animation in progress bar>"
}